Metadata-Version: 2.1
Name: axolotl-contribs-lgpl
Version: 0.0.2
Summary: LGPL contributions to the axolotl framework
Author: Wing Lian
License:                    GNU LESSER GENERAL PUBLIC LICENSE
Classifier: Programming Language :: Python :: 3
License-File: LICENSE
Requires-Dist: torch>=2.3.1
Requires-Dist: numpy<=2.0.1,>=1.24.4
Requires-Dist: datasets==3.1.0
